Metadata-Version: 2.1
Name: GitlabMRScanner
Version: 0.0.3
Summary: Minimal Security Bot that adds security code review for Gitlab Merge Requests
Home-page: UNKNOWN
Author: we45
Author-email: info@we45.com
License: MIT License
Platform: UNKNOWN
